everest/__init__.py
everest/basecamp.py
everest/config.py
everest/detrender.py
everest/dvs.py
everest/fits.py
everest/gp.py
everest/inject.py
everest/masksolve.py
everest/mathutils.py
everest/pool.py
everest/search.py
everest/standalone.py
everest/transit.py
everest/user.py
everest/utils.py
everest/missions/__init__.py
everest/missions/k2/__init__.py
everest/missions/k2/download.pbs
everest/missions/k2/k2.py
everest/missions/k2/pbs.py
everest/missions/k2/pipelines.py
everest/missions/k2/publish.pbs
everest/missions/k2/run.pbs
everest/missions/k2/sysrem.py
everest/missions/k2/utils.py
everest/missions/k2/tables/c00.stars
everest/missions/k2/tables/c00_everest1.cdpp
everest/missions/k2/tables/c00_everest1.out
everest/missions/k2/tables/c00_k2sff.cdpp
everest/missions/k2/tables/c00_k2sff.out
everest/missions/k2/tables/c00_nPLD.cdpp
everest/missions/k2/tables/c00_nPLD.sc.cdpp
everest/missions/k2/tables/c01.stars
everest/missions/k2/tables/c01_everest1.cdpp
everest/missions/k2/tables/c01_everest1.out
everest/missions/k2/tables/c01_k2sff.cdpp
everest/missions/k2/tables/c01_k2sff.out
everest/missions/k2/tables/c01_nPLD.cdpp
everest/missions/k2/tables/c01_nPLD.sc.cdpp
everest/missions/k2/tables/c02.stars
everest/missions/k2/tables/c02_everest1.cdpp
everest/missions/k2/tables/c02_everest1.out
everest/missions/k2/tables/c02_k2sff.cdpp
everest/missions/k2/tables/c02_k2sff.out
everest/missions/k2/tables/c02_nPLD.cdpp
everest/missions/k2/tables/c02_nPLD.sc.cdpp
everest/missions/k2/tables/c03.stars
everest/missions/k2/tables/c03_everest1.cdpp
everest/missions/k2/tables/c03_everest1.out
everest/missions/k2/tables/c03_k2sc.cdpp
everest/missions/k2/tables/c03_k2sc.out
everest/missions/k2/tables/c03_k2sff.cdpp
everest/missions/k2/tables/c03_k2sff.out
everest/missions/k2/tables/c03_nPLD.cdpp
everest/missions/k2/tables/c03_nPLD.sc.cdpp
everest/missions/k2/tables/c04.stars
everest/missions/k2/tables/c04_everest1.cdpp
everest_pipeline-2.0.11.dist-info/METADATA
everest_pipeline-2.0.11.dist-info/RECORD
everest_pipeline-2.0.11.dist-info/WHEEL
everest_pipeline-2.0.11.dist-info/top_level.txt
